<?xml version="1.0" encoding="utf-8"?>
<class id="9d3c3302-ba71-45ea-bd6a-db8e7bf631c1" type="Application" typeId="f40a4942-5d2d-4174-8ec1-af66cbd464db">
  <name>aryzac.io.Modules.Client.TestApplication</name>
  <display>aryzac.io.Modules.Client.TestApplication</display>
  <externalReference>259354b5-82fe-4c0a-bb30-1fda60b4d935</externalReference>
  <isAbstract>false</isAbstract>
  <order>1</order>
  <genericTypes />
  <isMapped>false</isMapped>
  <parentFolderId>df34c46e-7795-4624-bef1-de2358efb23f</parentFolderId>
  <diagram>
    <targetPackageId>37b32719-238a-447d-a201-565e91f60bab</targetPackageId>
  </diagram>
  <stereotypes />
  <metadata />
  <childElements />
</class>