<?xml version="1.0" encoding="utf-8"?>
<class id="3b5dc317-4e7d-44be-b2b0-3933f3dcc238" type="Designers Folder" typeId="dbb71aa5-0db2-4a2a-97a9-501950f36f99">
  <name>designers</name>
  <display>designers</display>
  <isAbstract>false</isAbstract>
  <sort-children>by-type-then-by-name</sort-children>
  <genericTypes />
  <isMapped>false</isMapped>
  <parentFolderId>7966642f-c3c5-47f3-a03b-0b758cc2a981</parentFolderId>
  <packageId>7966642f-c3c5-47f3-a03b-0b758cc2a981</packageId>
  <packageName>Aryzac.IO.Modules.Client</packageName>
  <stereotypes />
  <metadata />
  <childElements />
</class>